mcp_testcortexai/__init__.py
mcp_testcortexai/__main__.py
mcp_testcortexai/server.py
mcp_testcortexai-0.2.0.dist-info/METADATA
mcp_testcortexai-0.2.0.dist-info/WHEEL
mcp_testcortexai-0.2.0.dist-info/entry_points.txt
mcp_testcortexai-0.2.0.dist-info/top_level.txt
mcp_testcortexai-0.2.0.dist-info/RECORD
