Metadata-Version: 2.4
Name: mcp-testcortexai
Version: 0.2.0
Summary: TestCortex AI is a specialized quality engineering tool built on top of the Goose AI platform
Requires-Python: >=3.13.1
Requires-Dist: beautifulsoup4>=4.12.3
Requires-Dist: html2text>=2024.2.26
Requires-Dist: mcp[cli]>=1.9.1
Requires-Dist: requests>=2.32.3
